text_randomizer/__init__.py
text_randomizer/compiler.py
text_randomizer/lexer.py
text_randomizer/parser.py
text_randomizer/tokenizer.py
text_randomizer/utils.py
text_randomizer-0.0.3.dist-info/LICENSE
text_randomizer-0.0.3.dist-info/METADATA
text_randomizer-0.0.3.dist-info/WHEEL
text_randomizer-0.0.3.dist-info/top_level.txt
text_randomizer-0.0.3.dist-info/RECORD
