Metadata-Version: 2.1
Name: text-randomizer
Version: 0.0.3
Summary: Implementation of templating random values inside text
Author: Timur Zolotov TZbooo netbiom
Author-email: helloworldbooo@gmail.com
Maintainer: https://github.com/TZbooo
Maintainer-email: helloworldbooo@gmail.com
Keywords: text randomizer
License-File: LICENSE
